Metadata-Version: 2.1
Name: stream-magic
Version: 0.12
Summary: Support for controlling and querying network audio players                based on the StreamMagic platform by Cambridge Audio
Home-page: http://github.com/sebk-666/stream_magic/
Author: Sebastian Kaps
Author-email: seb.kaps@zoho.com
License: Apache Software License
Platform: any
Classifier: Programming Language :: Python
Classifier: Development Status :: 3 - Alpha
Classifier: Natural Language :: English
Classifier: Environment :: Console
Classifier: Intended Audience :: Developers
Classifier: License :: OSI Approved :: Apache Software License
Classifier: Operating System :: OS Independent
Classifier: Topic :: Home Automation
Provides-Extra: testing
